me_deploy/__init__.py
me_deploy/__main__.py
me_deploy/constants.py
me_deploy/main.py
me_deploy/mcu_tools.py
me_deploy/parser.py
me_deploy/tools.py
me_deploy/mcu_tools/ci_flashing/board_flash_wine.py
me_deploy/mcu_tools/ci_flashing/PNG/arrow.PNG
me_deploy/mcu_tools/ci_flashing/PNG/batch_done.PNG
me_deploy/mcu_tools/ci_flashing/PNG/connected.PNG
me_deploy/mcu_tools/ci_flashing/PNG/das_error.PNG
me_deploy/mcu_tools/ci_flashing/PNG/erase.PNG
me_deploy/mcu_tools/ci_flashing/PNG/exit.PNG
me_deploy/mcu_tools/ci_flashing/PNG/failed.PNG
me_deploy/mcu_tools/ci_flashing/PNG/ok_btn.PNG
me_deploy/mcu_tools/ci_flashing/PNG/start.PNG
me_deploy/mcu_tools/ci_flashing/PNG/success.PNG
me_deploy/mcu_tools/ci_flashing/memtool/AVKIT_Controller_TC39xB_tlfC_DAS.cfg
me_deploy/mcu_tools/ci_flashing/memtool/EPM51_EPM5_EPC5_TC38xA_das.cfg
me_deploy/mcu_tools/ci_flashing/memtool/GAS52_Sensorboard_TC39xB_das.cfg
me_deploy/mcu_tools/ci_flashing/memtool/TriBoard_TC29xB_das.cfg
me_deploy/mcu_tools/ci_flashing/memtool/TriBoard_TC36xA_das.cfg
me_deploy/mcu_tools/ci_flashing/memtool/TriBoard_TC38xA_das.cfg
me_deploy/mcu_tools/ci_flashing/memtool/appkit.cfg
me_deploy/mcu_tools/ci_flashing/memtool/epm58.cfg
me_deploy/mcu_tools/ci_flashing/memtool/gas52.cfg
me_deploy/mcu_tools/flashing/cli_shell.py
me_deploy/mcu_tools/flashing/flash_json_cfg.py
me_deploy/mcu_tools/flashing/utils/__init__.py
me_deploy/mcu_tools/flashing/utils/mcu_comms.py
me_deploy/mcu_tools/flashing/utils/mcu_hex_tools.py
me_deploy/mcu_tools/flashing/utils/mcu_netflash.py
me_deploy/mcu_tools/flashing/utils/mcu_xmodem.py
me_deploy/mcu_tools/flashing/utils/win_filesocket.py
me_deploy/resources/marvell/QE_0_patch/service_tim_for_qe_enable.bin
me_deploy/resources/marvell/mrvl88q_bin/mrvl88q_unified_info.s5
me_deploy/resources/marvell/mrvl88q_bin/mrvl88q_unified_upload.s5
me_deploy/resources/marvell/mrvl88q_bin/mrvl88q_unified_verify.s5
me_deploy/resources/marvell/mrvl88q_bin/utils_2/mrvl88q_conf_info_old.s5
me_deploy-2.0.0.dist-info/METADATA
me_deploy-2.0.0.dist-info/WHEEL
me_deploy-2.0.0.dist-info/entry_points.txt
me_deploy-2.0.0.dist-info/top_level.txt
me_deploy-2.0.0.dist-info/RECORD
