Metadata-Version: 2.1
Name: me-deploy
Version: 2.0.0
Summary: deploy base image to MobilEye boards.
Home-page: http://gitlab.mobileye.com/idof/me-deploy
Author: Ido Frenkel
Author-email: ido.frenkel@mobileye.com
Classifier: License :: OSI Approved :: MIT License
Classifier: Programming Language :: Python :: 3
Classifier: Programming Language :: Python :: 3 :: Only
Classifier: Programming Language :: Python :: Implementation :: CPython
Classifier: Programming Language :: Python :: Implementation :: PyPy
Requires-Python: >=3.7
Requires-Dist: intelhex
Requires-Dist: me-setups
Requires-Dist: psutil
Requires-Dist: xmodem
